{
  "pattern": 4,
  "facility": "中頭病院",
  "flow": "診療",
  "assignee": "hamaguchi",
  "spec_path": "docs/migration/gen1_中頭病院_診療.md",
  "base_path": "",
  "environment": "demo",
  "current_step": "commit",
  "qa_retry_count": 2,
  "validator_retry_count": 0,
  "outputs": {
    "design_spec": "C:\\Users\\hamaguchi.t\\vfb-中頭病院_診療\\output\\scenarios\\中頭病院_診療\\設計書_中頭病院_診療.yaml",
    "scaffold_json": "C:\\Users\\hamaguchi.t\\vfb-中頭病院_診療\\output\\json\\scaffold_中頭病院_診療.json",
    "draft_json": "C:\\Users\\hamaguchi.t\\vfb-中頭病院_診療\\output\\json\\draft_中頭病院_診療.json",
    "properties": "C:\\Users\\hamaguchi.t\\vfb-中頭病院_診療\\output\\scenarios\\中頭病院_診療\\properties_中頭病院_診療.md",
    "prompter_sidecar": "C:\\Users\\hamaguchi.t\\vfb-中頭病院_診療\\output\\scenarios\\中頭病院_診療\\prompts_中頭病院_診療.md",
    "prompted_json": "C:\\Users\\hamaguchi.t\\vfb-中頭病院_診療\\output\\json\\prompted_中頭病院_診療.json",
    "review_report": "C:\\Users\\hamaguchi.t\\vfb-中頭病院_診療\\output\\reports\\review_report_中頭病院_診療.md",
    "reviewed_json": "C:\\Users\\hamaguchi.t\\vfb-中頭病院_診療\\output\\json\\prompted_中頭病院_診療.json",
    "merged_json": "C:\\Users\\hamaguchi.t\\vfb-中頭病院_診療\\output\\json\\prompted_中頭病院_診療.json",
    "validator_report": "C:\\Users\\hamaguchi.t\\vfb-中頭病院_診療\\output\\reports\\validator_report_中頭病院_診療.md",
    "validator_json_report": "C:\\Users\\hamaguchi.t\\vfb-中頭病院_診療\\output\\reports\\validator_json_中頭病院_診療.json",
    "date_suffix": "20260507",
    "bivr": "C:\\Users\\hamaguchi.t\\vfb-中頭病院_診療\\output\\bivr\\中頭病院_診療_20260507.bivr",
    "test_report": "C:\\Users\\hamaguchi.t\\vfb-中頭病院_診療\\output\\reports\\test_report_中頭病院_診療.md",
    "validator_post_test_report": "C:\\Users\\hamaguchi.t\\vfb-中頭病院_診療\\output\\reports\\validator_post_test_report_中頭病院_診療.md"
  },
  "errors": [],
  "started_at": "2026-05-07T08:28:09.851494",
  "ended_at": "",
  "step_timings": {
    "branch": {
      "status": "ok",
      "seconds": 0,
      "started_at": "2026-05-01T19:39:02.124396"
    },
    "director": {
      "status": "ok",
      "seconds": 725.8,
      "started_at": "2026-05-07T08:28:09.853699",
      "tokens": {
        "input": 19,
        "output": 56428,
        "cache_read": 1721156,
        "cache_creation": 237193,
        "cost_usd": 0.0
      }
    },
    "qa": {
      "status": "ok",
      "seconds": 156.5,
      "started_at": "2026-05-07T08:40:15.691238",
      "tokens": {
        "input": 25,
        "output": 9867,
        "cache_read": 1250215,
        "cache_creation": 27367,
        "cost_usd": 0.0
      }
    },
    "copy_subflows": {
      "status": "ok",
      "seconds": 0.1,
      "started_at": "2026-05-07T08:42:52.204039"
    },
    "scaffold": {
      "status": "ok",
      "seconds": 0.1,
      "started_at": "2026-05-07T08:42:52.354371"
    },
    "layout": {
      "status": "ok",
      "seconds": 0.1,
      "started_at": "2026-05-07T08:42:52.489392"
    },
    "generator": {
      "status": "ok",
      "seconds": 0.1,
      "started_at": "2026-05-07T08:42:52.630175"
    },
    "prompter_props": {
      "status": "ok",
      "seconds": 292.8,
      "started_at": "2026-05-07T08:42:52.688431",
      "tokens": {
        "input": 6,
        "output": 22874,
        "cache_read": 77327,
        "cache_creation": 42771,
        "cost_usd": 0.0
      }
    },
    "reviewer": {
      "status": "ok",
      "seconds": 78.1,
      "started_at": "2026-05-07T08:47:45.494700",
      "tokens": {
        "input": 58,
        "output": 8738,
        "cache_read": 219318,
        "cache_creation": 47544,
        "cost_usd": 0.0
      }
    },
    "merge": {
      "status": "ok",
      "seconds": 0.0,
      "started_at": "2026-05-07T08:49:03.586627"
    },
    "validator": {
      "status": "ok",
      "seconds": 0.7,
      "started_at": "2026-05-07T08:49:03.590266"
    },
    "add_date": {
      "status": "ok",
      "seconds": 0.0,
      "started_at": "2026-05-07T08:49:04.262604"
    },
    "tester_build": {
      "status": "ok",
      "seconds": 1.0,
      "started_at": "2026-05-07T08:49:04.276840"
    },
    "tester": {
      "status": "ok",
      "seconds": 1.0
    },
    "build": {
      "status": "ok",
      "seconds": 0.7
    },
    "auto_fixer": {
      "status": "ok",
      "seconds": 0.7,
      "started_at": "2026-05-07T08:49:05.320585"
    },
    "fixer": {
      "status": "ok",
      "seconds": 0.0,
      "started_at": "2026-05-07T08:49:06.041993"
    },
    "collect_scenario": {
      "status": "ok",
      "seconds": 0.0,
      "started_at": "2026-05-07T08:49:06.063432"
    },
    "spec_html": {
      "status": "ok",
      "seconds": 0.6,
      "started_at": "2026-05-07T08:49:06.095324"
    },
    "commit": {
      "status": "running",
      "seconds": 0,
      "started_at": "2026-05-07T08:49:06.730816"
    }
  },
  "branch_name": "feature/中頭病院_診療",
  "skip_qa": false,
  "skip_tester": false,
  "unattended": true
}