{
  "question_type": "menu",
  "clarify_margin": 1,
  "numbers": {
    "1": "予約",
    "2": "変更",
    "3": "キャンセル",
    "4": "問い合わせ"
  },
  "synonyms": {
    "_YES_": [
      "はい",
      "ええ",
      "お願いします"
    ],
    "_NO_": [
      "いいえ",
      "結構です"
    ]
  },
  "extractors": [
    {
      "name": "birth_year",
      "regex": "(19[0-9][0-9]|20[0-9][0-9])(年|ねん)",
      "group": 1
    }
  ],
  "evidences": [
    {
      "name": "reservation",
      "keywords": [
        "予約",
        "よやく",
        "予定だっ",
        "お願いしてた",
        "入れてた"
      ],
      "negatable": true
    },
    {
      "name": "change_words",
      "keywords": [
        "変更",
        "へんこう",
        "変え",
        "かえ",
        "取り直し",
        "とりなおし",
        "ずらし",
        "ずらす",
        "ずらせ",
        "リスケ",
        "りすけ",
        "振り替え",
        "ふりかえ",
        "ふりかえ",
        "振替",
        "組み直し",
        "くみなおし",
        "繰り上げ",
        "くりあげ",
        "先延ばし",
        "さきのばし",
        "後ろ倒し",
        "うしろだおし",
        "延ばす",
        "のばす",
        "再設定",
        "さいせってい",
        "再調整",
        "さいちょうせい"
      ],
      "negatable": true
    },
    {
      "name": "cancel_words",
      "keywords": [
        "キャンセル",
        "取り消し",
        "とりけし",
        "やめ",
        "取りやめ",
        "とりやめ",
        "解除",
        "かいじょ"
      ],
      "patterns": [
        "(なし|無し)にして",
        "白紙に戻"
      ],
      "negatable": true
    },
    {
      "name": "operator",
      "patterns": [
        "(おぺれーたー|たんとうしゃ|にんげんのかた|まどぐち)(に|へ|と)?(つない|かわ|はなし|おねがい)"
      ]
    },
    {
      "name": "change_words_extra",
      "patterns": [
        "(別|べつ|ほか|他|違|ちが)(の|う)?日(程)?",
        "日を(改|あらた|延|のば|また)",
        "スケジュール(を|の)?(組み直|見直|調整)",
        "予定(を|の)?(見直|繰り上|組み直)",
        "いつもの(日|ひ)",
        "(今週|こんしゅう|今日|きょう)(じゃ|で)なく"
      ]
    },
    {
      "name": "cannot_visit",
      "patterns": [
        "(つごう|都合)が?(つかな(い|く)|わる(い|く)|あわな(い|く)|悪く)",
        "いけな(い|く)|行けな(い|く)",
        "(行か|いか)なきゃ",
        "間に合わな",
        "(難し|むずかし)くな",
        "終わらな",
        "(出張|しゅっちょう)",
        "(電車|でんしゃ|バス|ばす).*(止まっ|遅れ)",
        "(会議|かいぎ).*(入っ|はい)",
        "(シフト|しふと).*(変わ|合わな)",
        "(お腹|おなか).*(痛|いた)",
        "ばたばた",
        "別件",
        "無理",
        "ぎりぎり",
        "(天気|てんき).*(悪|わる)",
        "(予定|よてい)が(変わ|かわ)",
        "勘違い",
        "(仕事|しごと).*(休め|やすめ)",
        "親戚",
        "合わなく|合わない"
      ]
    },
    {
      "name": "future_date",
      "patterns": [
        "らいげつ|来月|らいしゅう|来週|べつのひ|別の日"
      ]
    },
    {
      "name": "inquiry_explicit",
      "keywords": [
        "質問",
        "しつもん",
        "問い合わせ",
        "といあわせ",
        "確認",
        "かくにん",
        "教えて",
        "おしえて",
        "相談",
        "そうだん",
        "聞きたい",
        "ききたい",
        "伺い",
        "うかがい",
        "知りたい",
        "しりたい",
        "よんばん",
        "待ち時間",
        "まちじかん",
        "いくら",
        "飛び込み",
        "とびこみ",
        "薬",
        "くすり",
        "れんとげん",
        "おうしん",
        "往診",
        "ふぁっくす"
      ],
      "patterns": [
        "(お聞き|おきき)(したい|してもいい)",
        "(分から|わから)(ない|なくて)",
        "(おしえてもらえますか|おしえていただけますか)",
        "(きいて|聞いて)(もいい|ていい|ください)",
        "どうすれば(いい|いいですか)",
        "(いた(い|かったり)|痛(い|かったり))"
      ]
    },
    {
      "name": "inquiry_vague",
      "patterns": [
        "ありますか",
        "いますか",
        "いけますか|行けますか",
        "どこですか|どこにありますか",
        "(ひつようですか|必要ですか)",
        "(みて|診て)(もらえますか|いただけますか|もらえる)",
        "(あいて|空いて)(いますか|ますか)",
        "(大丈夫|だいじょうぶ)ですか",
        "いつ(ですか|でしょうか|わかりますか|できますか)",
        "使えますか",
        "かかりますか|かかっちゃいますか",
        "(いつから|なんじから|何時から|なんじまで|何時まで|いつまで)",
        "(こんで|混んで)(ますか|いますか)",
        "(なんにちまえ|何日前)",
        "(やってます|やっています)(か|かね)?"
      ]
    }
  ],
  "events": [
    {
      "name": "ReservationCannotVisit",
      "all": [
        "reservation",
        "cannot_visit"
      ]
    },
    {
      "name": "WantAnotherDate",
      "all": [
        "ReservationCannotVisit",
        "future_date"
      ]
    }
  ],
  "rules": [
    {
      "intent": "変更",
      "all": [
        "WantAnotherDate"
      ]
    },
    {
      "intent": "変更",
      "all": [
        "ReservationCannotVisit"
      ]
    },
    {
      "intent": "変更",
      "all": [
        "reservation",
        "change_words"
      ]
    },
    {
      "intent": "キャンセル",
      "all": [
        "ReservationCannotVisit",
        "cancel_words"
      ]
    },
    {
      "intent": "キャンセル",
      "all": [
        "reservation",
        "cancel_words"
      ]
    },
    {
      "intent": "変更",
      "all": [
        "change_words"
      ],
      "none": [
        "change_words_neg"
      ]
    },
    {
      "intent": "変更",
      "all": [
        "change_words_extra"
      ]
    },
    {
      "intent": "変更",
      "all": [
        "reservation",
        "change_words_extra"
      ]
    },
    {
      "intent": "キャンセル",
      "all": [
        "cancel_words"
      ],
      "none": [
        "cancel_words_neg",
        "inquiry_explicit",
        "inquiry_vague"
      ]
    },
    {
      "intent": "キャンセル取りやめ",
      "all": [
        "cancel_words_neg"
      ],
      "none": [
        "change_words"
      ]
    },
    {
      "intent": "予約",
      "all": [
        "reservation",
        "inquiry_vague"
      ],
      "none": [
        "cannot_visit",
        "cancel_words",
        "change_words",
        "change_words_extra",
        "inquiry_explicit"
      ]
    },
    {
      "intent": "予約",
      "all": [
        "reservation"
      ],
      "none": [
        "cannot_visit",
        "cancel_words",
        "change_words",
        "change_words_extra",
        "inquiry_explicit",
        "inquiry_vague"
      ]
    },
    {
      "intent": "問い合わせ",
      "all": [
        "inquiry_explicit"
      ],
      "none": [
        "change_words",
        "change_words_extra"
      ]
    },
    {
      "intent": "CLARIFY",
      "all": [
        "inquiry_vague"
      ],
      "none": [
        "inquiry_explicit",
        "change_words",
        "change_words_extra"
      ]
    },
    {
      "intent": "TRANSFER_OPERATOR",
      "all": [
        "operator"
      ]
    }
  ]
}